powermate/__init__.py
powermate/demo.py
powermate-0.0.2.dist-info/DESCRIPTION.rst
powermate-0.0.2.dist-info/METADATA
powermate-0.0.2.dist-info/RECORD
powermate-0.0.2.dist-info/WHEEL
powermate-0.0.2.dist-info/entry_points.txt
powermate-0.0.2.dist-info/metadata.json
powermate-0.0.2.dist-info/top_level.txt
