Metadata-Version: 2.0
Name: powermate
Version: 0.0.2
Summary: Library for Griffin Powermate Bluetooth controllers
Home-page: https://github.com/auchter/powermate
Author: Michael Auchter
Author-email: a@phire.org
License: MIT
Keywords: powermate bluetooth
Platform: UNKNOWN
Classifier: Development Status :: 3 - Alpha
Classifier: License :: OSI Approved :: MIT License
Classifier: Programming Language :: Python :: 3.4
Requires-Dist: bluepy
